light_koreanbots/__init__.py
light_koreanbots-1.2.1.dist-info/LICENSE
light_koreanbots-1.2.1.dist-info/METADATA
light_koreanbots-1.2.1.dist-info/WHEEL
light_koreanbots-1.2.1.dist-info/top_level.txt
light_koreanbots-1.2.1.dist-info/RECORD
