Metadata-Version: 2.1
Name: light-koreanbots
Version: 1.2.1
Summary: (비공식) Koreanbots에 길드수 업데이트만 하는 모듈입니다.
Home-page: https://github.com/eunwoo1104/light-koreanbots
Author: eunwoo1104
Author-email: sions04@naver.com
License: UNKNOWN
Platform: UNKNOWN
Classifier: Programming Language :: Python :: 3
Requires-Python: >=3.6
